mlflow_migration/__init__.py
mlflow_migration/version.py
mlflow_migration/bulk/__init__.py
mlflow_migration/bulk/bulk_utils.py
mlflow_migration/bulk/experiments_merge_utils.py
mlflow_migration/bulk/export_all.py
mlflow_migration/bulk/export_experiments.py
mlflow_migration/bulk/export_models.py
mlflow_migration/bulk/import_experiments.py
mlflow_migration/bulk/import_models.py
mlflow_migration/bulk/model_utils.py
mlflow_migration/bulk/rename_utils.py
mlflow_migration/client/__init__.py
mlflow_migration/client/client_utils.py
mlflow_migration/client/databricks_cli_utils.py
mlflow_migration/client/databricks_utils.py
mlflow_migration/client/http_client.py
mlflow_migration/client/mlflow_auth_utils.py
mlflow_migration/client/user_agent_header.py
mlflow_migration/common/__init__.py
mlflow_migration/common/click_options.py
mlflow_migration/common/default_logging_config.py
mlflow_migration/common/dump_utils.py
mlflow_migration/common/filesystem.py
mlflow_migration/common/find_artifacts.py
mlflow_migration/common/io_utils.py
mlflow_migration/common/iterators.py
mlflow_migration/common/logging_utils.py
mlflow_migration/common/mlflow_utils.py
mlflow_migration/common/model_utils.py
mlflow_migration/common/pkg_version.py
mlflow_migration/common/source_tags.py
mlflow_migration/common/timestamp_utils.py
mlflow_migration/common/uc_permissions_utils.py
mlflow_migration/common/utils.py
mlflow_migration/common/ws_permissions_utils.py
mlflow_migration/copy/__init__.py
mlflow_migration/copy/click_options.py
mlflow_migration/copy/copy_model_version.py
mlflow_migration/copy/copy_run.py
mlflow_migration/copy/copy_utils.py
mlflow_migration/experiment/__init__.py
mlflow_migration/experiment/export_experiment.py
mlflow_migration/experiment/import_experiment.py
mlflow_migration/experiment/nested_runs_utils.py
mlflow_migration/experiment/oss_nested_runs_utils.py
mlflow_migration/model/__init__.py
mlflow_migration/model/export_model.py
mlflow_migration/model/import_model.py
mlflow_migration-1.0.2.dist-info/licenses/LICENSE
mlflow_migration-1.0.2.dist-info/METADATA
mlflow_migration-1.0.2.dist-info/WHEEL
mlflow_migration-1.0.2.dist-info/entry_points.txt
mlflow_migration-1.0.2.dist-info/top_level.txt
mlflow_migration-1.0.2.dist-info/RECORD
